prolintpy/__init__.py
prolintpy/core/__init__.py
prolintpy/core/computecontacts.py
prolintpy/core/systemtopology.py
prolintpy/utils/__init__.py
prolintpy/utils/martinilipids.py
prolintpy/utils/metrics.py
prolintpy/utils/misc.py
prolintpy/utils/network.py
prolintpy/utils/shift_range.py
prolintpy/vis/__init__.py
prolintpy/vis/show_contact_projection.py
prolintpy/vis/show_density.py
prolintpy/vis/show_distances.py
prolintpy/vis/show_metric_distances.py
prolintpy/vis/show_network.py
prolintpy/vis/show_points.py
prolintpy/vis/show_radar.py
prolintpy-0.9.7.dist-info/LICENSE
prolintpy-0.9.7.dist-info/METADATA
prolintpy-0.9.7.dist-info/WHEEL
prolintpy-0.9.7.dist-info/top_level.txt
prolintpy-0.9.7.dist-info/RECORD
