Metadata-Version: 2.1
Name: prolintpy
Version: 0.9.7
Summary: Automated analyis and visualization of lipid-protein interactions.
Home-page: https://github.com/ProLint/prolintpy
Author: Besian I. Sejdiu
Author-email: besian.sejdiu@stjude.org
License: MIT
Platform: UNKNOWN
Requires-Python: >=3.6
License-File: LICENSE
Requires-Dist: numpy
Requires-Dist: pandas (==0.24.0)
Requires-Dist: scipy
Requires-Dist: mdtraj (==1.9.5)
Requires-Dist: pyyaml
Requires-Dist: colorcet
Requires-Dist: bokeh (==1.4.0)
Requires-Dist: networkx
Requires-Dist: jupyterlab
Requires-Dist: nglview
Requires-Dist: matplotlib
